MANIFEST.in
README.md
setup.py
mlbriefcase/__init__.py
mlbriefcase/base.py
mlbriefcase/briefcase-schema.json
mlbriefcase/briefcase.py
mlbriefcase/credentialprovider.py
mlbriefcase/datasource.py
mlbriefcase.egg-info/PKG-INFO
mlbriefcase.egg-info/SOURCES.txt
mlbriefcase.egg-info/dependency_links.txt
mlbriefcase.egg-info/requires.txt
mlbriefcase.egg-info/top_level.txt
mlbriefcase/amazon/__init__.py
mlbriefcase/amazon/aws_boto3.py
mlbriefcase/amazon/comprehend.py
mlbriefcase/amazon/rekognition.py
mlbriefcase/amazon/s3.py
mlbriefcase/azure/__init__.py
mlbriefcase/azure/azure_resource.py
mlbriefcase/azure/keyvault.py
mlbriefcase/azure/storage.py
mlbriefcase/azure/subscription.py
mlbriefcase/azure/tenant.py
mlbriefcase/azure/auth/__init__.py
mlbriefcase/azure/auth/managed_service_identity.py
mlbriefcase/azure/auth/serviceprincipal.py
mlbriefcase/azure/auth/user_with_device_code.py
mlbriefcase/azure/cognitiveservice/__init__.py
mlbriefcase/azure/cognitiveservice/anomalydetection.py
mlbriefcase/azure/cognitiveservice/contentmoderator.py
mlbriefcase/azure/cognitiveservice/face.py
mlbriefcase/azure/cognitiveservice/spellcheck.py
mlbriefcase/azure/cognitiveservice/textanalytics.py
mlbriefcase/azure/cognitiveservice/vision.py
mlbriefcase/clarifai/__init__.py
mlbriefcase/clarifai/clarifai.py
mlbriefcase/common/__init__.py
mlbriefcase/google/__init__.py
mlbriefcase/google/google_base.py
mlbriefcase/google/language.py
mlbriefcase/google/video.py
mlbriefcase/google/vision.py
mlbriefcase/python/__init__.py
mlbriefcase/python/jupyterlab_credentialprovider.py
mlbriefcase/python/keyring.py
mlbriefcase/python/sqlalchemy.py