Metadata-Version: 2.1
Name: mlbriefcase
Version: 0.1
Summary: Manages your cloud resources across multiple executing environments.
Home-page: http://github.com/Microsoft/Briefcase
Author: Markus Cozowicz
Author-email: marcozo@microsoft.com
License: UNKNOWN
Keywords: cloud security resources
Platform: UNKNOWN
Classifier: Development Status :: 3 - Alpha
Classifier: Intended Audience :: Developers
Classifier: Intended Audience :: Science/Research
Classifier: Topic :: Software Development
Classifier: License :: OSI Approved :: MIT License
Classifier: Programming Language :: Python :: 3
Classifier: Programming Language :: Python :: 3.4
Classifier: Programming Language :: Python :: 3.5
Classifier: Programming Language :: Python :: 3.6
Classifier: Programming Language :: Python :: 3.7
Requires-Python: >=3
Provides-Extra: test
